juntagrico_crowdfunding/__init__.py
juntagrico_crowdfunding/admin.py
juntagrico_crowdfunding/apps.py
juntagrico_crowdfunding/config.py
juntagrico_crowdfunding/forms.py
juntagrico_crowdfunding/mailer.py
juntagrico_crowdfunding/middleware.py
juntagrico_crowdfunding/models.py
juntagrico_crowdfunding/urls.py
juntagrico_crowdfunding/views.py
juntagrico_crowdfunding/entity/__init__.py
juntagrico_crowdfunding/entity/fund.py
juntagrico_crowdfunding/entity/fundable.py
juntagrico_crowdfunding/entity/funder.py
juntagrico_crowdfunding/entity/funding_project.py
juntagrico_crowdfunding/migrations/0001_initial.py
juntagrico_crowdfunding/migrations/0002_auto_20181124_1739.py
juntagrico_crowdfunding/migrations/0003_auto_20181124_1741.py
juntagrico_crowdfunding/migrations/__init__.py
juntagrico_crowdfunding/templates/cf/confirm.html
juntagrico_crowdfunding/templates/cf/contribution.html
juntagrico_crowdfunding/templates/cf/fund.html
juntagrico_crowdfunding/templates/cf/funder_menu.html
juntagrico_crowdfunding/templates/cf/guest_menu.html
juntagrico_crowdfunding/templates/cf/list_fundables.html
juntagrico_crowdfunding/templates/cf/list_funding_projects.html
juntagrico_crowdfunding/templates/cf/public_access_wrapper.html
juntagrico_crowdfunding/templates/cf/session_lost.html
juntagrico_crowdfunding/templates/cf/signup.html
juntagrico_crowdfunding/templates/cf/thanks.html
juntagrico_crowdfunding/templates/cf/view_fundable.html
juntagrico_crowdfunding/templates/cf/mails/fund_confirmation_mail.txt
juntagrico_crowdfunding/templates/juntagrico/menu/user.html
juntagrico_crowdfunding/templatetags/__init__.py
juntagrico_crowdfunding/templatetags/crowdfunding_config.py
juntagrico_crowdfunding/util/__init__.py
juntagrico_crowdfunding/util/auth.py
juntagrico_crowdfunding-1.7.0.dist-info/licenses/LICENSE
juntagrico_crowdfunding-1.7.0.dist-info/METADATA
juntagrico_crowdfunding-1.7.0.dist-info/WHEEL
juntagrico_crowdfunding-1.7.0.dist-info/top_level.txt
juntagrico_crowdfunding-1.7.0.dist-info/RECORD
